movie_ls/__init__.py
movie_ls/__version__.py
movie_ls/driver.py
movie_ls/web_page_extractor.py
movie_ls/parsers/__init__.py
movie_ls/parsers/hdhub4u_html_parser.py
movie_ls/services/__init__.py
movie_ls/services/mediator_page.py
movie_link_scrape-1.0.0.dist-info/LICENSE
movie_link_scrape-1.0.0.dist-info/METADATA
movie_link_scrape-1.0.0.dist-info/WHEEL
movie_link_scrape-1.0.0.dist-info/top_level.txt
movie_link_scrape-1.0.0.dist-info/RECORD
