Metadata-Version: 2.1
Name: movie-link-scrape
Version: 1.0.0
License-File: LICENSE
Requires-Dist: beautifulsoup4 ==4.13.4
Requires-Dist: selenium ==4.34.2
